setup.py
vbt3/__init__.py
vbt3/data.py
vbt3/fixed_psi.py
vbt3/functions.py
vbt3/molecule.py
vbt3/numerical.py
vbt3/orbital_permutations.py
vbt3/slaterdet.py
vbt3/test_fixed_psi.py
vbt3/test_functions.py
vbt3/test_molecule.py
vbt3/test_numerical.py
vbt3/test_slaterdet.py
vbt3.egg-info/PKG-INFO
vbt3.egg-info/SOURCES.txt
vbt3.egg-info/dependency_links.txt
vbt3.egg-info/requires.txt
vbt3.egg-info/top_level.txt
vbt3.egg-info/zip-safe