Metadata-Version: 2.1
Name: vbt3
Version: 1.114
Summary: Symbolic calculations for semi-quantitative Valence Bond Theory
Home-page: http://github.com/talipovm/vbt3
Author: Marat Talipov
Author-email: talipovm@nmsu.edu
License: MIT
Platform: UNKNOWN
